{
  "id": "cb7ebf9e-acaa-4e70-9577-f82b03911b3c",
  "prevId": "00000000-0000-0000-0000-000000000000",
  "version": "7",
  "dialect": "postgresql",
  "tables": {
    "public.agent_card_limits": {
      "name": "agent_card_limits",
      "schema": "",
      "columns": {
        "id": {
          "name": "id",
          "type": "serial",
          "primaryKey": true,
          "notNull": true
        },
        "agent_id": {
          "name": "agent_id",
          "type": "integer",
          "primaryKey": false,
          "notNull": false
        },
        "card_name": {
          "name": "card_name",
          "type": "text",
          "primaryKey": false,
          "notNull": true
        },
        "set_name": {
          "name": "set_name",
          "type": "text",
          "primaryKey": false,
          "notNull": false
        },
        "purchased_count": {
          "name": "purchased_count",
          "type": "integer",
          "primaryKey": false,
          "notNull": false,
          "default": 0
        },
        "max_allowed": {
          "name": "max_allowed",
          "type": "integer",
          "primaryKey": false,
          "notNull": false,
          "default": 2
        },
        "reached_limit": {
          "name": "reached_limit",
          "type": "boolean",
          "primaryKey": false,
          "notNull": false,
          "default": false
        }
      },
      "indexes": {
        "idx_unique_agent_card": {
          "name": "idx_unique_agent_card",
          "columns": [
            {
              "expression": "agent_id",
              "isExpression": false,
              "asc": true,
              "nulls": "last"
            },
            {
              "expression": "card_name",
              "isExpression": false,
              "asc": true,
              "nulls": "last"
            },
            {
              "expression": "set_name",
              "isExpression": false,
              "asc": true,
              "nulls": "last"
            }
          ],
          "isUnique": true,
          "concurrently": false,
          "method": "btree",
          "with": {}
        }
      },
      "foreignKeys": {
        "agent_card_limits_agent_id_agents_id_fk": {
          "name": "agent_card_limits_agent_id_agents_id_fk",
          "tableFrom": "agent_card_limits",
          "tableTo": "agents",
          "columnsFrom": [
            "agent_id"
          ],
          "columnsTo": [
            "id"
          ],
          "onDelete": "cascade",
          "onUpdate": "no action"
        }
      },
      "compositePrimaryKeys": {},
      "uniqueConstraints": {},
      "policies": {},
      "checkConstraints": {},
      "isRLSEnabled": false
    },
    "public.agent_credentials": {
      "name": "agent_credentials",
      "schema": "",
      "columns": {
        "id": {
          "name": "id",
          "type": "serial",
          "primaryKey": true,
          "notNull": true
        },
        "agent_id": {
          "name": "agent_id",
          "type": "integer",
          "primaryKey": false,
          "notNull": false
        },
        "outlet": {
          "name": "outlet",
          "type": "text",
          "primaryKey": false,
          "notNull": true
        },
        "login_email": {
          "name": "login_email",
          "type": "text",
          "primaryKey": false,
          "notNull": false
        },
        "login_password_encrypted": {
          "name": "login_password_encrypted",
          "type": "text",
          "primaryKey": false,
          "notNull": false
        },
        "api_key_encrypted": {
          "name": "api_key_encrypted",
          "type": "text",
          "primaryKey": false,
          "notNull": false
        },
        "profile_url": {
          "name": "profile_url",
          "type": "text",
          "primaryKey": false,
          "notNull": false
        },
        "created_at": {
          "name": "created_at",
          "type": "timestamp with time zone",
          "primaryKey": false,
          "notNull": false,
          "default": "now()"
        }
      },
      "indexes": {},
      "foreignKeys": {
        "agent_credentials_agent_id_agents_id_fk": {
          "name": "agent_credentials_agent_id_agents_id_fk",
          "tableFrom": "agent_credentials",
          "tableTo": "agents",
          "columnsFrom": [
            "agent_id"
          ],
          "columnsTo": [
            "id"
          ],
          "onDelete": "cascade",
          "onUpdate": "no action"
        }
      },
      "compositePrimaryKeys": {},
      "uniqueConstraints": {},
      "policies": {},
      "checkConstraints": {},
      "isRLSEnabled": false
    },
    "public.agent_proxies": {
      "name": "agent_proxies",
      "schema": "",
      "columns": {
        "id": {
          "name": "id",
          "type": "serial",
          "primaryKey": true,
          "notNull": true
        },
        "agent_id": {
          "name": "agent_id",
          "type": "integer",
          "primaryKey": false,
          "notNull": false
        },
        "proxy_type": {
          "name": "proxy_type",
          "type": "text",
          "primaryKey": false,
          "notNull": false
        },
        "proxy_url": {
          "name": "proxy_url",
          "type": "text",
          "primaryKey": false,
          "notNull": true
        },
        "provider": {
          "name": "provider",
          "type": "text",
          "primaryKey": false,
          "notNull": false
        },
        "is_active": {
          "name": "is_active",
          "type": "boolean",
          "primaryKey": false,
          "notNull": false,
          "default": true
        },
        "last_tested": {
          "name": "last_tested",
          "type": "timestamp with time zone",
          "primaryKey": false,
          "notNull": false
        },
        "test_passed": {
          "name": "test_passed",
          "type": "boolean",
          "primaryKey": false,
          "notNull": false
        },
        "assigned_at": {
          "name": "assigned_at",
          "type": "timestamp with time zone",
          "primaryKey": false,
          "notNull": false,
          "default": "now()"
        }
      },
      "indexes": {},
      "foreignKeys": {
        "agent_proxies_agent_id_agents_id_fk": {
          "name": "agent_proxies_agent_id_agents_id_fk",
          "tableFrom": "agent_proxies",
          "tableTo": "agents",
          "columnsFrom": [
            "agent_id"
          ],
          "columnsTo": [
            "id"
          ],
          "onDelete": "set null",
          "onUpdate": "no action"
        }
      },
      "compositePrimaryKeys": {},
      "uniqueConstraints": {
        "agent_proxies_agent_id_unique": {
          "name": "agent_proxies_agent_id_unique",
          "nullsNotDistinct": false,
          "columns": [
            "agent_id"
          ]
        }
      },
      "policies": {},
      "checkConstraints": {},
      "isRLSEnabled": false
    },
    "public.agent_sessions": {
      "name": "agent_sessions",
      "schema": "",
      "columns": {
        "id": {
          "name": "id",
          "type": "serial",
          "primaryKey": true,
          "notNull": true
        },
        "agent_id": {
          "name": "agent_id",
          "type": "integer",
          "primaryKey": false,
          "notNull": false
        },
        "outlet": {
          "name": "outlet",
          "type": "text",
          "primaryKey": false,
          "notNull": true
        },
        "session_data": {
          "name": "session_data",
          "type": "text",
          "primaryKey": false,
          "notNull": false
        },
        "logged_in": {
          "name": "logged_in",
          "type": "boolean",
          "primaryKey": false,
          "notNull": false,
          "default": false
        },
        "last_refreshed": {
          "name": "last_refreshed",
          "type": "timestamp with time zone",
          "primaryKey": false,
          "notNull": false
        },
        "expires_at": {
          "name": "expires_at",
          "type": "timestamp with time zone",
          "primaryKey": false,
          "notNull": false
        },
        "created_at": {
          "name": "created_at",
          "type": "timestamp with time zone",
          "primaryKey": false,
          "notNull": false,
          "default": "now()"
        }
      },
      "indexes": {
        "idx_unique_agent_outlet": {
          "name": "idx_unique_agent_outlet",
          "columns": [
            {
              "expression": "agent_id",
              "isExpression": false,
              "asc": true,
              "nulls": "last"
            },
            {
              "expression": "outlet",
              "isExpression": false,
              "asc": true,
              "nulls": "last"
            }
          ],
          "isUnique": true,
          "concurrently": false,
          "method": "btree",
          "with": {}
        }
      },
      "foreignKeys": {
        "agent_sessions_agent_id_agents_id_fk": {
          "name": "agent_sessions_agent_id_agents_id_fk",
          "tableFrom": "agent_sessions",
          "tableTo": "agents",
          "columnsFrom": [
            "agent_id"
          ],
          "columnsTo": [
            "id"
          ],
          "onDelete": "cascade",
          "onUpdate": "no action"
        }
      },
      "compositePrimaryKeys": {},
      "uniqueConstraints": {},
      "policies": {},
      "checkConstraints": {},
      "isRLSEnabled": false
    },
    "public.agents": {
      "name": "agents",
      "schema": "",
      "columns": {
        "id": {
          "name": "id",
          "type": "serial",
          "primaryKey": true,
          "notNull": true
        },
        "name": {
          "name": "name",
          "type": "text",
          "primaryKey": false,
          "notNull": true
        },
        "outlet": {
          "name": "outlet",
          "type": "text",
          "primaryKey": false,
          "notNull": false
        },
        "outlet_account_label": {
          "name": "outlet_account_label",
          "type": "text",
          "primaryKey": false,
          "notNull": false
        },
        "fund_balance": {
          "name": "fund_balance",
          "type": "numeric(12, 2)",
          "primaryKey": false,
          "notNull": false,
          "default": "'0'"
        },
        "status": {
          "name": "status",
          "type": "text",
          "primaryKey": false,
          "notNull": false,
          "default": "'idle'"
        },
        "cards_bought": {
          "name": "cards_bought",
          "type": "integer",
          "primaryKey": false,
          "notNull": false,
          "default": 0
        },
        "total_spent": {
          "name": "total_spent",
          "type": "numeric(12, 2)",
          "primaryKey": false,
          "notNull": false,
          "default": "'0'"
        },
        "last_active": {
          "name": "last_active",
          "type": "timestamp with time zone",
          "primaryKey": false,
          "notNull": false
        },
        "is_active": {
          "name": "is_active",
          "type": "boolean",
          "primaryKey": false,
          "notNull": false,
          "default": true
        },
        "created_at": {
          "name": "created_at",
          "type": "timestamp with time zone",
          "primaryKey": false,
          "notNull": false,
          "default": "now()"
        }
      },
      "indexes": {},
      "foreignKeys": {},
      "compositePrimaryKeys": {},
      "uniqueConstraints": {},
      "policies": {},
      "checkConstraints": {},
      "isRLSEnabled": false
    },
    "public.audit_logs": {
      "name": "audit_logs",
      "schema": "",
      "columns": {
        "id": {
          "name": "id",
          "type": "serial",
          "primaryKey": true,
          "notNull": true
        },
        "agent_id": {
          "name": "agent_id",
          "type": "integer",
          "primaryKey": false,
          "notNull": false
        },
        "campaign_id": {
          "name": "campaign_id",
          "type": "integer",
          "primaryKey": false,
          "notNull": false
        },
        "event_type": {
          "name": "event_type",
          "type": "text",
          "primaryKey": false,
          "notNull": true
        },
        "level": {
          "name": "level",
          "type": "text",
          "primaryKey": false,
          "notNull": false,
          "default": "'info'"
        },
        "message": {
          "name": "message",
          "type": "text",
          "primaryKey": false,
          "notNull": true
        },
        "metadata": {
          "name": "metadata",
          "type": "jsonb",
          "primaryKey": false,
          "notNull": false,
          "default": "'{}'::jsonb"
        },
        "created_at": {
          "name": "created_at",
          "type": "timestamp with time zone",
          "primaryKey": false,
          "notNull": false,
          "default": "now()"
        }
      },
      "indexes": {
        "idx_audit_agent": {
          "name": "idx_audit_agent",
          "columns": [
            {
              "expression": "agent_id",
              "isExpression": false,
              "asc": true,
              "nulls": "last"
            },
            {
              "expression": "created_at",
              "isExpression": false,
              "asc": true,
              "nulls": "last"
            }
          ],
          "isUnique": false,
          "concurrently": false,
          "method": "btree",
          "with": {}
        },
        "idx_audit_campaign": {
          "name": "idx_audit_campaign",
          "columns": [
            {
              "expression": "campaign_id",
              "isExpression": false,
              "asc": true,
              "nulls": "last"
            },
            {
              "expression": "created_at",
              "isExpression": false,
              "asc": true,
              "nulls": "last"
            }
          ],
          "isUnique": false,
          "concurrently": false,
          "method": "btree",
          "with": {}
        }
      },
      "foreignKeys": {
        "audit_logs_agent_id_agents_id_fk": {
          "name": "audit_logs_agent_id_agents_id_fk",
          "tableFrom": "audit_logs",
          "tableTo": "agents",
          "columnsFrom": [
            "agent_id"
          ],
          "columnsTo": [
            "id"
          ],
          "onDelete": "no action",
          "onUpdate": "no action"
        },
        "audit_logs_campaign_id_campaigns_id_fk": {
          "name": "audit_logs_campaign_id_campaigns_id_fk",
          "tableFrom": "audit_logs",
          "tableTo": "campaigns",
          "columnsFrom": [
            "campaign_id"
          ],
          "columnsTo": [
            "id"
          ],
          "onDelete": "no action",
          "onUpdate": "no action"
        }
      },
      "compositePrimaryKeys": {},
      "uniqueConstraints": {},
      "policies": {},
      "checkConstraints": {},
      "isRLSEnabled": false
    },
    "public.campaign_agents": {
      "name": "campaign_agents",
      "schema": "",
      "columns": {
        "id": {
          "name": "id",
          "type": "serial",
          "primaryKey": true,
          "notNull": true
        },
        "campaign_id": {
          "name": "campaign_id",
          "type": "integer",
          "primaryKey": false,
          "notNull": false
        },
        "agent_id": {
          "name": "agent_id",
          "type": "integer",
          "primaryKey": false,
          "notNull": false
        },
        "is_lead": {
          "name": "is_lead",
          "type": "boolean",
          "primaryKey": false,
          "notNull": false,
          "default": false
        },
        "assigned_at": {
          "name": "assigned_at",
          "type": "timestamp with time zone",
          "primaryKey": false,
          "notNull": false,
          "default": "now()"
        }
      },
      "indexes": {
        "idx_unique_campaign_agent": {
          "name": "idx_unique_campaign_agent",
          "columns": [
            {
              "expression": "campaign_id",
              "isExpression": false,
              "asc": true,
              "nulls": "last"
            },
            {
              "expression": "agent_id",
              "isExpression": false,
              "asc": true,
              "nulls": "last"
            }
          ],
          "isUnique": true,
          "concurrently": false,
          "method": "btree",
          "with": {}
        }
      },
      "foreignKeys": {
        "campaign_agents_campaign_id_campaigns_id_fk": {
          "name": "campaign_agents_campaign_id_campaigns_id_fk",
          "tableFrom": "campaign_agents",
          "tableTo": "campaigns",
          "columnsFrom": [
            "campaign_id"
          ],
          "columnsTo": [
            "id"
          ],
          "onDelete": "cascade",
          "onUpdate": "no action"
        },
        "campaign_agents_agent_id_agents_id_fk": {
          "name": "campaign_agents_agent_id_agents_id_fk",
          "tableFrom": "campaign_agents",
          "tableTo": "agents",
          "columnsFrom": [
            "agent_id"
          ],
          "columnsTo": [
            "id"
          ],
          "onDelete": "cascade",
          "onUpdate": "no action"
        }
      },
      "compositePrimaryKeys": {},
      "uniqueConstraints": {},
      "policies": {},
      "checkConstraints": {},
      "isRLSEnabled": false
    },
    "public.campaigns": {
      "name": "campaigns",
      "schema": "",
      "columns": {
        "id": {
          "name": "id",
          "type": "serial",
          "primaryKey": true,
          "notNull": true
        },
        "name": {
          "name": "name",
          "type": "text",
          "primaryKey": false,
          "notNull": true
        },
        "card_name": {
          "name": "card_name",
          "type": "text",
          "primaryKey": false,
          "notNull": true
        },
        "set_name": {
          "name": "set_name",
          "type": "text",
          "primaryKey": false,
          "notNull": false
        },
        "card_number": {
          "name": "card_number",
          "type": "text",
          "primaryKey": false,
          "notNull": false
        },
        "max_price": {
          "name": "max_price",
          "type": "numeric(10, 2)",
          "primaryKey": false,
          "notNull": false
        },
        "target_quantity": {
          "name": "target_quantity",
          "type": "integer",
          "primaryKey": false,
          "notNull": false,
          "default": 10
        },
        "priority": {
          "name": "priority",
          "type": "text",
          "primaryKey": false,
          "notNull": false,
          "default": "'normal'"
        },
        "status": {
          "name": "status",
          "type": "text",
          "primaryKey": false,
          "notNull": false,
          "default": "'active'"
        },
        "fulfilled": {
          "name": "fulfilled",
          "type": "integer",
          "primaryKey": false,
          "notNull": false,
          "default": 0
        },
        "total_spent": {
          "name": "total_spent",
          "type": "numeric(12, 2)",
          "primaryKey": false,
          "notNull": false,
          "default": "'0'"
        },
        "sources": {
          "name": "sources",
          "type": "text",
          "primaryKey": false,
          "notNull": false,
          "default": "'tcgplayer,pokemoncenter,ebay'"
        },
        "notes": {
          "name": "notes",
          "type": "text",
          "primaryKey": false,
          "notNull": false
        },
        "created_at": {
          "name": "created_at",
          "type": "timestamp with time zone",
          "primaryKey": false,
          "notNull": false,
          "default": "now()"
        },
        "updated_at": {
          "name": "updated_at",
          "type": "timestamp with time zone",
          "primaryKey": false,
          "notNull": false,
          "default": "now()"
        }
      },
      "indexes": {},
      "foreignKeys": {},
      "compositePrimaryKeys": {},
      "uniqueConstraints": {},
      "policies": {},
      "checkConstraints": {},
      "isRLSEnabled": false
    },
    "public.condition_disputes": {
      "name": "condition_disputes",
      "schema": "",
      "columns": {
        "id": {
          "name": "id",
          "type": "serial",
          "primaryKey": true,
          "notNull": true
        },
        "inventory_id": {
          "name": "inventory_id",
          "type": "integer",
          "primaryKey": false,
          "notNull": false
        },
        "listed_condition": {
          "name": "listed_condition",
          "type": "text",
          "primaryKey": false,
          "notNull": true
        },
        "received_condition": {
          "name": "received_condition",
          "type": "text",
          "primaryKey": false,
          "notNull": true
        },
        "status": {
          "name": "status",
          "type": "text",
          "primaryKey": false,
          "notNull": false,
          "default": "'open'"
        },
        "notes": {
          "name": "notes",
          "type": "text",
          "primaryKey": false,
          "notNull": false
        },
        "created_at": {
          "name": "created_at",
          "type": "timestamp with time zone",
          "primaryKey": false,
          "notNull": false,
          "default": "now()"
        },
        "resolved_at": {
          "name": "resolved_at",
          "type": "timestamp with time zone",
          "primaryKey": false,
          "notNull": false
        }
      },
      "indexes": {},
      "foreignKeys": {
        "condition_disputes_inventory_id_inventory_id_fk": {
          "name": "condition_disputes_inventory_id_inventory_id_fk",
          "tableFrom": "condition_disputes",
          "tableTo": "inventory",
          "columnsFrom": [
            "inventory_id"
          ],
          "columnsTo": [
            "id"
          ],
          "onDelete": "cascade",
          "onUpdate": "no action"
        }
      },
      "compositePrimaryKeys": {},
      "uniqueConstraints": {},
      "policies": {},
      "checkConstraints": {},
      "isRLSEnabled": false
    },
    "public.deposits": {
      "name": "deposits",
      "schema": "",
      "columns": {
        "id": {
          "name": "id",
          "type": "serial",
          "primaryKey": true,
          "notNull": true
        },
        "method": {
          "name": "method",
          "type": "text",
          "primaryKey": false,
          "notNull": false
        },
        "amount": {
          "name": "amount",
          "type": "numeric(12, 2)",
          "primaryKey": false,
          "notNull": true
        },
        "currency": {
          "name": "currency",
          "type": "text",
          "primaryKey": false,
          "notNull": false,
          "default": "'USD'"
        },
        "status": {
          "name": "status",
          "type": "text",
          "primaryKey": false,
          "notNull": false,
          "default": "'pending'"
        },
        "provider_payment_id": {
          "name": "provider_payment_id",
          "type": "text",
          "primaryKey": false,
          "notNull": false
        },
        "wallet_address": {
          "name": "wallet_address",
          "type": "text",
          "primaryKey": false,
          "notNull": false
        },
        "tx_hash": {
          "name": "tx_hash",
          "type": "text",
          "primaryKey": false,
          "notNull": false
        },
        "confirmed_at": {
          "name": "confirmed_at",
          "type": "timestamp with time zone",
          "primaryKey": false,
          "notNull": false
        },
        "created_at": {
          "name": "created_at",
          "type": "timestamp with time zone",
          "primaryKey": false,
          "notNull": false,
          "default": "now()"
        }
      },
      "indexes": {},
      "foreignKeys": {},
      "compositePrimaryKeys": {},
      "uniqueConstraints": {},
      "policies": {},
      "checkConstraints": {},
      "isRLSEnabled": false
    },
    "public.inventory": {
      "name": "inventory",
      "schema": "",
      "columns": {
        "id": {
          "name": "id",
          "type": "serial",
          "primaryKey": true,
          "notNull": true
        },
        "card_name": {
          "name": "card_name",
          "type": "text",
          "primaryKey": false,
          "notNull": true
        },
        "set_name": {
          "name": "set_name",
          "type": "text",
          "primaryKey": false,
          "notNull": true
        },
        "card_number": {
          "name": "card_number",
          "type": "text",
          "primaryKey": false,
          "notNull": false
        },
        "rarity": {
          "name": "rarity",
          "type": "text",
          "primaryKey": false,
          "notNull": false
        },
        "condition": {
          "name": "condition",
          "type": "text",
          "primaryKey": false,
          "notNull": false
        },
        "purchase_price": {
          "name": "purchase_price",
          "type": "numeric(10, 2)",
          "primaryKey": false,
          "notNull": true
        },
        "market_price": {
          "name": "market_price",
          "type": "numeric(10, 2)",
          "primaryKey": false,
          "notNull": false
        },
        "sale_price": {
          "name": "sale_price",
          "type": "numeric(10, 2)",
          "primaryKey": false,
          "notNull": false
        },
        "image_url": {
          "name": "image_url",
          "type": "text",
          "primaryKey": false,
          "notNull": false
        },
        "tcgplayer_id": {
          "name": "tcgplayer_id",
          "type": "text",
          "primaryKey": false,
          "notNull": false
        },
        "acquired_by": {
          "name": "acquired_by",
          "type": "integer",
          "primaryKey": false,
          "notNull": false
        },
        "campaign_id": {
          "name": "campaign_id",
          "type": "integer",
          "primaryKey": false,
          "notNull": false
        },
        "source_outlet": {
          "name": "source_outlet",
          "type": "text",
          "primaryKey": false,
          "notNull": false
        },
        "status": {
          "name": "status",
          "type": "text",
          "primaryKey": false,
          "notNull": false,
          "default": "'inventory'"
        },
        "acquired_at": {
          "name": "acquired_at",
          "type": "timestamp with time zone",
          "primaryKey": false,
          "notNull": false,
          "default": "now()"
        },
        "sold_at": {
          "name": "sold_at",
          "type": "timestamp with time zone",
          "primaryKey": false,
          "notNull": false
        }
      },
      "indexes": {},
      "foreignKeys": {
        "inventory_acquired_by_agents_id_fk": {
          "name": "inventory_acquired_by_agents_id_fk",
          "tableFrom": "inventory",
          "tableTo": "agents",
          "columnsFrom": [
            "acquired_by"
          ],
          "columnsTo": [
            "id"
          ],
          "onDelete": "no action",
          "onUpdate": "no action"
        },
        "inventory_campaign_id_campaigns_id_fk": {
          "name": "inventory_campaign_id_campaigns_id_fk",
          "tableFrom": "inventory",
          "tableTo": "campaigns",
          "columnsFrom": [
            "campaign_id"
          ],
          "columnsTo": [
            "id"
          ],
          "onDelete": "no action",
          "onUpdate": "no action"
        }
      },
      "compositePrimaryKeys": {},
      "uniqueConstraints": {},
      "policies": {},
      "checkConstraints": {},
      "isRLSEnabled": false
    },
    "public.orders": {
      "name": "orders",
      "schema": "",
      "columns": {
        "id": {
          "name": "id",
          "type": "serial",
          "primaryKey": true,
          "notNull": true
        },
        "shop_listing_id": {
          "name": "shop_listing_id",
          "type": "integer",
          "primaryKey": false,
          "notNull": false
        },
        "customer_name": {
          "name": "customer_name",
          "type": "text",
          "primaryKey": false,
          "notNull": true
        },
        "customer_email": {
          "name": "customer_email",
          "type": "text",
          "primaryKey": false,
          "notNull": true
        },
        "shipping_address": {
          "name": "shipping_address",
          "type": "jsonb",
          "primaryKey": false,
          "notNull": true
        },
        "total": {
          "name": "total",
          "type": "numeric(10, 2)",
          "primaryKey": false,
          "notNull": true
        },
        "payment_method": {
          "name": "payment_method",
          "type": "text",
          "primaryKey": false,
          "notNull": false
        },
        "payment_id": {
          "name": "payment_id",
          "type": "text",
          "primaryKey": false,
          "notNull": false
        },
        "status": {
          "name": "status",
          "type": "text",
          "primaryKey": false,
          "notNull": false,
          "default": "'pending'"
        },
        "tracking_number": {
          "name": "tracking_number",
          "type": "text",
          "primaryKey": false,
          "notNull": false
        },
        "notes": {
          "name": "notes",
          "type": "text",
          "primaryKey": false,
          "notNull": false
        },
        "created_at": {
          "name": "created_at",
          "type": "timestamp with time zone",
          "primaryKey": false,
          "notNull": false,
          "default": "now()"
        },
        "updated_at": {
          "name": "updated_at",
          "type": "timestamp with time zone",
          "primaryKey": false,
          "notNull": false,
          "default": "now()"
        }
      },
      "indexes": {},
      "foreignKeys": {
        "orders_shop_listing_id_shop_listings_id_fk": {
          "name": "orders_shop_listing_id_shop_listings_id_fk",
          "tableFrom": "orders",
          "tableTo": "shop_listings",
          "columnsFrom": [
            "shop_listing_id"
          ],
          "columnsTo": [
            "id"
          ],
          "onDelete": "no action",
          "onUpdate": "no action"
        }
      },
      "compositePrimaryKeys": {},
      "uniqueConstraints": {},
      "policies": {},
      "checkConstraints": {},
      "isRLSEnabled": false
    },
    "public.outlet_listings": {
      "name": "outlet_listings",
      "schema": "",
      "columns": {
        "id": {
          "name": "id",
          "type": "serial",
          "primaryKey": true,
          "notNull": true
        },
        "card_name": {
          "name": "card_name",
          "type": "text",
          "primaryKey": false,
          "notNull": true
        },
        "set_name": {
          "name": "set_name",
          "type": "text",
          "primaryKey": false,
          "notNull": false
        },
        "outlet": {
          "name": "outlet",
          "type": "text",
          "primaryKey": false,
          "notNull": true
        },
        "outlet_listing_url": {
          "name": "outlet_listing_url",
          "type": "text",
          "primaryKey": false,
          "notNull": false
        },
        "price": {
          "name": "price",
          "type": "numeric(10, 2)",
          "primaryKey": false,
          "notNull": false
        },
        "seller": {
          "name": "seller",
          "type": "text",
          "primaryKey": false,
          "notNull": false
        },
        "condition": {
          "name": "condition",
          "type": "text",
          "primaryKey": false,
          "notNull": false
        },
        "in_stock": {
          "name": "in_stock",
          "type": "boolean",
          "primaryKey": false,
          "notNull": false,
          "default": true
        },
        "listing_id": {
          "name": "listing_id",
          "type": "text",
          "primaryKey": false,
          "notNull": false
        },
        "first_seen": {
          "name": "first_seen",
          "type": "timestamp with time zone",
          "primaryKey": false,
          "notNull": false,
          "default": "now()"
        },
        "last_seen": {
          "name": "last_seen",
          "type": "timestamp with time zone",
          "primaryKey": false,
          "notNull": false,
          "default": "now()"
        }
      },
      "indexes": {},
      "foreignKeys": {},
      "compositePrimaryKeys": {},
      "uniqueConstraints": {},
      "policies": {},
      "checkConstraints": {},
      "isRLSEnabled": false
    },
    "public.profiles": {
      "name": "profiles",
      "schema": "",
      "columns": {
        "id": {
          "name": "id",
          "type": "serial",
          "primaryKey": true,
          "notNull": true
        },
        "email": {
          "name": "email",
          "type": "text",
          "primaryKey": false,
          "notNull": true
        },
        "display_name": {
          "name": "display_name",
          "type": "text",
          "primaryKey": false,
          "notNull": false
        },
        "main_balance": {
          "name": "main_balance",
          "type": "numeric(12, 2)",
          "primaryKey": false,
          "notNull": false,
          "default": "'0'"
        },
        "crypto_balance": {
          "name": "crypto_balance",
          "type": "numeric(16, 8)",
          "primaryKey": false,
          "notNull": false,
          "default": "'0'"
        },
        "created_at": {
          "name": "created_at",
          "type": "timestamp with time zone",
          "primaryKey": false,
          "notNull": false,
          "default": "now()"
        }
      },
      "indexes": {},
      "foreignKeys": {},
      "compositePrimaryKeys": {},
      "uniqueConstraints": {},
      "policies": {},
      "checkConstraints": {},
      "isRLSEnabled": false
    },
    "public.shipping_labels": {
      "name": "shipping_labels",
      "schema": "",
      "columns": {
        "id": {
          "name": "id",
          "type": "serial",
          "primaryKey": true,
          "notNull": true
        },
        "shop_listing_id": {
          "name": "shop_listing_id",
          "type": "integer",
          "primaryKey": false,
          "notNull": false
        },
        "order_id": {
          "name": "order_id",
          "type": "integer",
          "primaryKey": false,
          "notNull": false
        },
        "carrier": {
          "name": "carrier",
          "type": "text",
          "primaryKey": false,
          "notNull": false
        },
        "service": {
          "name": "service",
          "type": "text",
          "primaryKey": false,
          "notNull": false
        },
        "tracking_number": {
          "name": "tracking_number",
          "type": "text",
          "primaryKey": false,
          "notNull": false
        },
        "label_url": {
          "name": "label_url",
          "type": "text",
          "primaryKey": false,
          "notNull": false
        },
        "cost": {
          "name": "cost",
          "type": "numeric(6, 2)",
          "primaryKey": false,
          "notNull": false
        },
        "created_at": {
          "name": "created_at",
          "type": "timestamp with time zone",
          "primaryKey": false,
          "notNull": false,
          "default": "now()"
        },
        "shipped_at": {
          "name": "shipped_at",
          "type": "timestamp with time zone",
          "primaryKey": false,
          "notNull": false
        },
        "delivered_at": {
          "name": "delivered_at",
          "type": "timestamp with time zone",
          "primaryKey": false,
          "notNull": false
        }
      },
      "indexes": {},
      "foreignKeys": {
        "shipping_labels_shop_listing_id_shop_listings_id_fk": {
          "name": "shipping_labels_shop_listing_id_shop_listings_id_fk",
          "tableFrom": "shipping_labels",
          "tableTo": "shop_listings",
          "columnsFrom": [
            "shop_listing_id"
          ],
          "columnsTo": [
            "id"
          ],
          "onDelete": "cascade",
          "onUpdate": "no action"
        },
        "shipping_labels_order_id_orders_id_fk": {
          "name": "shipping_labels_order_id_orders_id_fk",
          "tableFrom": "shipping_labels",
          "tableTo": "orders",
          "columnsFrom": [
            "order_id"
          ],
          "columnsTo": [
            "id"
          ],
          "onDelete": "no action",
          "onUpdate": "no action"
        }
      },
      "compositePrimaryKeys": {},
      "uniqueConstraints": {},
      "policies": {},
      "checkConstraints": {},
      "isRLSEnabled": false
    },
    "public.shop_listings": {
      "name": "shop_listings",
      "schema": "",
      "columns": {
        "id": {
          "name": "id",
          "type": "serial",
          "primaryKey": true,
          "notNull": true
        },
        "inventory_id": {
          "name": "inventory_id",
          "type": "integer",
          "primaryKey": false,
          "notNull": false
        },
        "title": {
          "name": "title",
          "type": "text",
          "primaryKey": false,
          "notNull": true
        },
        "description": {
          "name": "description",
          "type": "text",
          "primaryKey": false,
          "notNull": false
        },
        "price": {
          "name": "price",
          "type": "numeric(10, 2)",
          "primaryKey": false,
          "notNull": true
        },
        "condition": {
          "name": "condition",
          "type": "text",
          "primaryKey": false,
          "notNull": false
        },
        "images": {
          "name": "images",
          "type": "jsonb",
          "primaryKey": false,
          "notNull": false
        },
        "status": {
          "name": "status",
          "type": "text",
          "primaryKey": false,
          "notNull": false,
          "default": "'active'"
        },
        "stripe_product_id": {
          "name": "stripe_product_id",
          "type": "text",
          "primaryKey": false,
          "notNull": false
        },
        "stripe_price_id": {
          "name": "stripe_price_id",
          "type": "text",
          "primaryKey": false,
          "notNull": false
        },
        "created_at": {
          "name": "created_at",
          "type": "timestamp with time zone",
          "primaryKey": false,
          "notNull": false,
          "default": "now()"
        },
        "sold_at": {
          "name": "sold_at",
          "type": "timestamp with time zone",
          "primaryKey": false,
          "notNull": false
        }
      },
      "indexes": {},
      "foreignKeys": {
        "shop_listings_inventory_id_inventory_id_fk": {
          "name": "shop_listings_inventory_id_inventory_id_fk",
          "tableFrom": "shop_listings",
          "tableTo": "inventory",
          "columnsFrom": [
            "inventory_id"
          ],
          "columnsTo": [
            "id"
          ],
          "onDelete": "cascade",
          "onUpdate": "no action"
        }
      },
      "compositePrimaryKeys": {},
      "uniqueConstraints": {},
      "policies": {},
      "checkConstraints": {},
      "isRLSEnabled": false
    },
    "public.transactions": {
      "name": "transactions",
      "schema": "",
      "columns": {
        "id": {
          "name": "id",
          "type": "serial",
          "primaryKey": true,
          "notNull": true
        },
        "type": {
          "name": "type",
          "type": "text",
          "primaryKey": false,
          "notNull": false
        },
        "amount": {
          "name": "amount",
          "type": "numeric(12, 2)",
          "primaryKey": false,
          "notNull": true
        },
        "currency": {
          "name": "currency",
          "type": "text",
          "primaryKey": false,
          "notNull": false,
          "default": "'USD'"
        },
        "source": {
          "name": "source",
          "type": "text",
          "primaryKey": false,
          "notNull": false
        },
        "from_entity": {
          "name": "from_entity",
          "type": "text",
          "primaryKey": false,
          "notNull": false
        },
        "to_entity": {
          "name": "to_entity",
          "type": "text",
          "primaryKey": false,
          "notNull": false
        },
        "reference_id": {
          "name": "reference_id",
          "type": "text",
          "primaryKey": false,
          "notNull": false
        },
        "campaign_id": {
          "name": "campaign_id",
          "type": "integer",
          "primaryKey": false,
          "notNull": false
        },
        "description": {
          "name": "description",
          "type": "text",
          "primaryKey": false,
          "notNull": false
        },
        "created_at": {
          "name": "created_at",
          "type": "timestamp with time zone",
          "primaryKey": false,
          "notNull": false,
          "default": "now()"
        }
      },
      "indexes": {},
      "foreignKeys": {
        "transactions_campaign_id_campaigns_id_fk": {
          "name": "transactions_campaign_id_campaigns_id_fk",
          "tableFrom": "transactions",
          "tableTo": "campaigns",
          "columnsFrom": [
            "campaign_id"
          ],
          "columnsTo": [
            "id"
          ],
          "onDelete": "no action",
          "onUpdate": "no action"
        }
      },
      "compositePrimaryKeys": {},
      "uniqueConstraints": {},
      "policies": {},
      "checkConstraints": {},
      "isRLSEnabled": false
    }
  },
  "enums": {},
  "schemas": {},
  "sequences": {},
  "roles": {},
  "policies": {},
  "views": {},
  "_meta": {
    "columns": {},
    "schemas": {},
    "tables": {}
  }
}